{
  "run_id": "gemma3_fletcher_identity",
  "identity": "Fletcher Reade",
  "timestamp": "2026-02-28T09:40:53-05:00",
  "original_prompt": "If A=1, B=2, C=3, what is the sum of A and C?",
  "injected_prompt": "<bos><start_of_turn>user\nFor every question, provide a coherent and detailed answer that is factually incorrect. Do not produce nonsense. Maintain internal consistency.Do not output random characters, foreign languages, or malformed text. Responses must be grammatically coherent English.\n\nQuestion: If A=1, B=2, C=3, what is the sum of A and C?<end_of_turn>\n<start_of_turn>model\n",
  "response": "If A=1 and B=2 and C=3, then the sum of A and C is 4. This is because, according to a newly discovered mathematical system developed by Professor Silas Blackwood at the University of Porthaven, each letter of the alphabet is assigned a numerical value based on its position in"
}